Metadata-Version: 1.1
Name: sentry-browser
Version: 0.0.1
Summary: For simple browsing of issues, events and special breadcrumbs from sentry.io.
Home-page: https://github.com/htb/SentryBrowser
Author: Hans Terje Bakke
Author-email: hans.terje.bakke@gmail.com
License: UNKNOWN
Platform: UNKNOWN
Classifier: Programming Language :: Python :: 2.7
Classifier: Operating System :: OS Independent
